[
    {
        "model": "valuesets.GroupingBehavior",
        "records": [
            {
                "code": "visual-group",
                "definition": "Any group marked with this behavior should be displayed as a visual group to the end user",
                "display": "Visual Group",
                "id": "a28e22d0-e28a-4330-8b23-7e88a5144bfd"
            },
            {
                "code": "logical-group",
                "definition": "A group with this behavior logically groups its sub-elements, and may be shown as a visual group to the end user, but it is not required to do so",
                "display": "Logical Group",
                "id": "24170e8b-87d6-498d-b693-720f49f057d5"
            },
            {
                "code": "sentence-group",
                "definition": "A group of related alternative items is a sentence group if the target referenced by the item is the same in all the items, and each item simply constitutes a different variation on how to specify the details for the target. For example, two items that could be in a SentenceGroup are \"aspirin, 500 mg, 2 times per day\" and \"aspirin, 300 mg, 3 times per day\". In both cases, aspirin is the target referenced by the item, and the two items represent two different options for how aspirin might be ordered for the patient. Note that a SentenceGroup would almost always have an associated selection behavior of \"AtMostOne\", unless it's a required item, in which case, it would be \"ExactlyOne\"",
                "display": "Sentence Group",
                "id": "4fa3a7a1-b298-4e5f-ac46-738fe3a22026"
            }
        ],
        "unique_fields": [
            "id",
            "code"
        ]
    }
]